{"chunk_definitions":[{"row":15,"row_count":1,"visible":true,"expansion_state":0,"options":{"engine":"r","label":"setup","include":false},"document_id":"D577B6D3","chunk_id":"csetup_chunk","chunk_label":"setup"},{"row":25,"row_count":1,"visible":true,"expansion_state":0,"options":{"engine":"r","label":"unnamed-chunk-3"},"document_id":"D577B6D3","chunk_id":"cznrmaempny26","chunk_label":"unnamed-chunk-1"},{"row":92,"row_count":1,"visible":true,"expansion_state":0,"options":{"engine":"r","label":"unnamed-chunk-22"},"document_id":"D577B6D3","chunk_id":"cigdg2v8npia6","chunk_label":"unnamed-chunk-2"},{"row":115,"row_count":1,"visible":true,"expansion_state":0,"options":{"engine":"r","label":"unnamed-chunk-69"},"document_id":"D577B6D3","chunk_id":"cl0cs0qoawko9","chunk_label":"unnamed-chunk-3"},{"row":127,"row_count":1,"visible":true,"expansion_state":0,"options":{"engine":"r","label":"unnamed-chunk-72"},"document_id":"D577B6D3","chunk_id":"c47uc89viu84x","chunk_label":"unnamed-chunk-4"},{"row":146,"row_count":1,"visible":true,"expansion_state":0,"options":{"engine":"r","label":"unnamed-chunk-92"},"document_id":"D577B6D3","chunk_id":"ca4j71omg0of4","chunk_label":"unnamed-chunk-5"}],"doc_write_time":1659364388,"working_dir":null,"default_chunk_options":{"echo":true},"chunk_rendered_width":700}